urpatimeout/__about__.py
urpatimeout/__init__.py
urpatimeout/py.typed
urpatimeout/timeout.py
urpatimeout-0.2.2.dist-info/LICENSE
urpatimeout-0.2.2.dist-info/METADATA
urpatimeout-0.2.2.dist-info/WHEEL
urpatimeout-0.2.2.dist-info/top_level.txt
urpatimeout-0.2.2.dist-info/RECORD
