Metadata-Version: 2.1
Name: urpatimeout
Version: 0.2.2
Summary: Modul for managing timeouts inside UltimateRPA
Home-page: https://github.com/ultimaterpa/urpatimeout
Author: SlavaQQ
Author-email: support@ultimaterpa.cz
License: MIT
Keywords: Robotic Process Automation,RPA,UltimateRPA,timeout,time limit
Platform: UNKNOWN
Classifier: License :: OSI Approved :: MIT License
Requires-Python: >=3.7
